LICENSE
MANIFEST.in
README.md
setup.py
pybattleships/__init__.py
pybattleships/board.py
pybattleships/game.py
pybattleships/ship.py
pybattleships.egg-info/PKG-INFO
pybattleships.egg-info/SOURCES.txt
pybattleships.egg-info/dependency_links.txt
pybattleships.egg-info/not-zip-safe
pybattleships.egg-info/top_level.txt
pybattleships/doc/Makefile
pybattleships/doc/source/board.rst
pybattleships/doc/source/conf.py
pybattleships/doc/source/game.rst
pybattleships/doc/source/index.rst
pybattleships/doc/source/ship.rst