Metadata-Version: 1.1
Name: pybattleships
Version: 0.1.1
Summary: A Python Battleship framework
Home-page: http://github.com/RobinSikkens/pybattleships
Author: Robin Sikkens & Maarten van den Berg
Author-email: pybattleships@robinsikkens.nl
License: MIT
Keywords: sticky woestgaaf battleship
Platform: UNKNOWN
Classifier: Development Status :: 3 - Alpha
Classifier: License :: OSI Approved :: MIT License
Classifier: Programming Language :: Python :: 3
